bstconnect/LICENSE
bstconnect/README.MD
bstconnect/__init__.py
bstconnect/requirements.txt
bstconnect/thirdparty.json
bstconnect-0.14.dist-info/LICENSE.rst
bstconnect-0.14.dist-info/METADATA
bstconnect-0.14.dist-info/WHEEL
bstconnect-0.14.dist-info/top_level.txt
bstconnect-0.14.dist-info/RECORD
